it_assistant/__init__.py
it_assistant/ailyapp_client.py
it_assistant/config.py
it_assistant/do_ai.py
it_assistant/intent_detail.py
it_assistant/lark_client.py
it_assistant/logger.py
it_assistant/openapi.py
it_assistant/test.py
main/__init__.py
main/ailyapp_client.py
main/do_ai.py
main/intent_detail.py
main/lark_client.py
main/logger.py
it_assistant-0.1.14.dist-info/METADATA
it_assistant-0.1.14.dist-info/WHEEL
it_assistant-0.1.14.dist-info/top_level.txt
it_assistant-0.1.14.dist-info/RECORD
