Metadata-Version: 2.4
Name: it_assistant
Version: 0.1.14
Summary: 新增退还时的spuid
Home-page: https://github.com/liujunmei/it_assistant
Author: liujunmei
Author-email: liujunmei@bytedance.com
Classifier: Programming Language :: Python :: 3
Classifier: License :: OSI Approved :: MIT License
Classifier: Operating System :: OS Independent
Requires-Python: >=3.6
Requires-Dist: requests>=2.25.1
Requires-Dist: numpy>=1.20.0
Dynamic: author
Dynamic: author-email
Dynamic: classifier
Dynamic: description
Dynamic: description-content-type
Dynamic: home-page
Dynamic: requires-dist
Dynamic: requires-python
Dynamic: summary
